{
  "version": "7",
  "dialect": "postgresql",
  "entries": [
    {
      "idx": 0,
      "version": "7",
      "when": 1752154822118,
      "tag": "0000_burly_jackpot",
      "breakpoints": true
    },
    {
      "idx": 1,
      "version": "7",
      "when": 1753819439513,
      "tag": "0001_eminent_leo",
      "breakpoints": true
    },
    {
      "idx": 2,
      "version": "7",
      "when": 1754594124443,
      "tag": "0002_great_dust",
      "breakpoints": true
    },
    {
      "idx": 3,
      "version": "7",
      "when": 1757068800000,
      "tag": "0003_webauthn_ceremony_fix",
      "breakpoints": true
    },
    {
      "idx": 4,
      "version": "7",
      "when": 1757069800000,
      "tag": "0004_webauthn_cleanup_indexes",
      "breakpoints": true
    }
  ]
}
